Workbook

Sheet IS Current
B1: Income Statement
B2: For the period June 1 – August 31, 2026
B4: Rent used — June | D4: -650
B5: Repair collected — Dana R. | D5: 120
B6: Parts used — Dana R. | D6: -10
B7: Repair collected — Marcus T. | D7: 150
B8: Repair collected — Priya S. | D8: 270
B9: Parts used — Priya S. | D9: -25
B10: Repair collected — Liam O. | D10: 300
B11: Parts used — Liam O. | D11: -95
B12: Repair collected — Sofia M. | D12: 150
B13: Repair collected — Jamal W. | D13: 360
B14: Parts used — Jamal W. | D14: -60
B15: Repair collected — Erin K. | D15: 225
... B48: Depreciation — laptop, Summer 2026 | D48: -30

Sheet IS Final
B1: Income Statement
B2: For the period June 1 – August 31, 2026
B4: Revenue
B5: Repair services | D5: =SUMIF('IS Current'!D4:D48,">0")
B6: Total revenue | D6: =D5
B8: Expenses
B9: Parts used | D9: =-SUMPRODUCT(--ISNUMBER(SEARCH("Parts used",'IS Current'!B4:B48)),'IS Current'!D4:D48)
B10: Rent | D10: =-SUMPRODUCT(--ISNUMBER(SEARCH("Rent used",'IS Current'!B4:B48)),'IS Current'!D4:D48)
B11: Depreciation | D11: =-SUMPRODUCT(--ISNUMBER(SEARCH("Depreciation",'IS Current'!B4:B48)),'IS Current'!D4:D48)
B12: Total expenses | D12: =SUM(D9:D11)
B14: Net income | D14: =D6-D12

Sheet MC Current
B1: Statement of Members' Capital
B2: For the period June 1 – August 31, 2026
B4: CONTRIBUTED
B5: Cash — covered from your personal funds (May) | D5: 160
B6: Laptop — brought from home (May) | D6: 610
B7: Equipment — gear from home — grinder, headset press, shop vacuum (May) | D7: 220
B8: Cash — deposited to open the LLC bank account (June 1) | D8: 1300
B9: Balance, June 1, 2026 | D9: =SUM(D5:D8)
B10: Balance, August 31, 2026 | D10: =D9
B12: GENERATED
B13: Repair collected — Brake job + Tune-up + Tire mounting ×2 @ $70 | D13: 340
B14: Repair collected — Walk-ins — mixed work (no itemized detail) | D14: 180
B15: Repair collected — Tune-up | D15: 80
B16: Repair collected — Brake overhaul | D16: 140
B17: Repair collected — Chain + cassette replacement | D17: 130
B18: Repair collected — Tune-up + minor repair | D18: 100
B19: Repair collected — Custom wheel work + new spokes | D19: 150
B20: Parts used — May | D20: -300
B21: Rent used — May | D21: -650
B22: Balance, June 1, 2026 | D22: =SUM(D13:D21)
B23: Rent used — June | D23: -650
B24: Repair collected — Dana R. | D24: 120
B25: Parts used — Dana R. | D25: -10
B26: Repair collected — Marcus T. | D26: 150
B27: Repair collected — Priya S. | D27: 270
B28: Parts used — Priya S. | D28: -25
B29: Repair collected — Liam O. | D29: 300
B30: Parts used — Liam O. | D30: -95
B31: Repair collected — Sofia M. | D31: 150
B32: Repair collected — Jamal W. | D32: 360
B33: Parts used — Jamal W. | D33: -60
B34: Repair collected — Erin K. | D34: 225
... B67: Depreciation — laptop, Summer 2026 | D67: -30
B68: Balance, August 31, 2026 | D68: =D22+SUM(D23:D67)
B70: WITHDRAWN
B71: Owner's draw — money taken out for personal use | D71: -600
B72: Balance, August 31, 2026 | D72: =SUM(D71:D71)

Sheet MC Final
B1: Statement of Members' Capital
B2: For the period June 1 – August 31, 2026
C4: Contributed | D4: Generated | E4: Withdrawn | F4: Total
B5: Balance, June 1, 2026 | C5: ='MC Current'!D9 | D5: ='MC Current'!D22 | E5: — | F5: =SUM(C5:E5)
B6: Add: Contributions | C6: — | D6: — | E6: — | F6: —
B7: Add: Net income | C7: — | D7: ='IS Final'!D14 | E7: — | F7: =SUM(C7:E7)
B8: Less: Owner's draw | C8: — | D8: — | E8: ='MC Current'!D72 | F8: =SUM(C8:E8)
B9: Balance, August 31, 2026 | C9: =SUM(C5:C8) | D9: =SUM(D5:D8) | E9: =SUM(E5:E8) | F9: =SUM(C9:E9)

Sheet CF Current
B1: Cash Flow Statement
B2: For the period June 1 – August 31, 2026
B4: Repair collected — Dana R. | D4: 120
B5: Repair collected — Marcus T. | D5: 150
B6: Repair collected — Priya S. | D6: 270
B7: Repair collected — Liam O. | D7: 300
B8: Repair collected — Sofia M. | D8: 150
B9: Repair collected — Jamal W. | D9: 360
B10: Repair collected — Erin K. | D10: 225
B11: Repair collected — Noah B. | D11: 210
B12: Repair collected — Grace L. | D12: 240
B13: Repair collected — Theo H. | D13: 240
B14: Repair collected — Maya P. | D14: 450
B15: Repair collected — Owen C. | D15: 360
... B31: Money taken out for personal use | D31: -600

Sheet CF Final
B1: Cash Flow Statement
B2: For the period June 1 – August 31, 2026
B4: Operating activities
B5: Collected from repair customers | D5: =SUMIF('CF Current'!D4:D31,">0")
B6: Parts purchased | D6: =SUMPRODUCT(--ISNUMBER(SEARCH("Parts bought",'CF Current'!B4:B31)),'CF Current'!D4:D31)
B7: Rent paid | D7: =SUMPRODUCT(--ISNUMBER(SEARCH("Rent paid",'CF Current'!B4:B31)),'CF Current'!D4:D31)
B8: Cash from operating activities | D8: =SUM(D5:D7)
B10: Investing activities
B11: Purchased repair tool | D11: =SUMPRODUCT(--ISNUMBER(SEARCH("New repair tool",'CF Current'!B4:B31)),'CF Current'!D4:D31)
B12: Cash used in investing activities | D12: =SUM(D11:D11)
B14: Financing activities
B15: Paid off credit card | D15: =SUMPRODUCT(--ISNUMBER(SEARCH("Credit card",'CF Current'!B4:B31)),'CF Current'!D4:D31)
B16: Owner's draw | D16: =SUMPRODUCT(--ISNUMBER(SEARCH("Money taken out",'CF Current'!B4:B31)),'CF Current'!D4:D31)
B17: Cash used in financing activities | D17: =SUM(D15:D16)
B19: Net change in cash | D19: =D8+D12+D17
B20: Cash, June 1, 2026 | D20: 1300
B21: Cash, August 31, 2026 | D21: =D20+D19
